Workbook

Sheet Annual_Summary
A1: Month No. (महिना क्र.) | B1: Month Name (English) | C1: Month Name (मराठी) | D1: Total Receipts / Income (जमा) | E1: Total Payments / Expenses (खर्च) | F1: Closing Balance (अखेर शिल्लक)
A2: 1 | B2: January | C2: जानेवारी | D2: ='January'!D20 | E2: ='January'!H19 | F2: ='January'!H20
A3: 2 | B3: February | C3: फेब्रुवारी | D3: ='February'!D20 | E3: ='February'!H19 | F3: ='February'!H20
A4: 3 | B4: March | C4: मार्च | D4: ='March'!D20 | E4: ='March'!H19 | F4: ='March'!H20
A5: 4 | B5: April | C5: एप्रिल | D5: ='April'!D20 | E5: ='April'!H19 | F5: ='April'!H20
A6: 5 | B6: May | C6: मे | D6: ='May'!D20 | E6: ='May'!H19 | F6: ='May'!H20
A7: 6 | B7: June | C7: जून | D7: ='June'!D20 | E7: ='June'!H19 | F7: ='June'!H20
A8: 7 | B8: July | C8: जुलै | D8: ='July'!D20 | E8: ='July'!H19 | F8: ='July'!H20
A9: 8 | B9: August | C9: ऑगस्ट | D9: ='August'!D20 | E9: ='August'!H19 | F9: ='August'!H20
A10: 9 | B10: September | C10: सप्टेंबर | D10: ='September'!D20 | E10: ='September'!H19 | F10: ='September'!H20
A11: 10 | B11: October | C11: ऑक्टोबर | D11: ='October'!D20 | E11: ='October'!H19 | F11: ='October'!H20
A12: 11 | B12: November | C12: नोव्हेंबर | D12: ='November'!D20 | E12: ='November'!H19 | F12: ='November'!H20
A13: 12 | B13: December | C13: डिसेंबर | D13: ='December'!D20 | E13: ='December'!H19 | F13: ='December'!H20

Sheet January
A1: Date (तारीख) [Receipts] | B1: Particulars (तपशील / नावे) | C1: L.F. | D1: Amount (रक्कम) | E1: Date (तारीख) [Payments] | F1: Particulars (तपशील / जमा) | G1: L.F. | H1: Amount (रक्कम)
B2: To Opening Balance (सुरुवातीची शिल्लक) | D2: 0
F19: By Closing Balance c/d (अखेरची शिल्लक) | H19: =D20-SUM(H2:H18)
A20: Total (एकूण) | D20: =SUM(D2:D19) | E20: Total (एकूण) | H20: =SUM(H2:H19)

Sheet February
A1: Date (तारीख) [Receipts] | B1: Particulars (तपशील / नावे) | C1: L.F. | D1: Amount (रक्कम) | E1: Date (तारीख) [Payments] | F1: Particulars (तपशील / जमा) | G1: L.F. | H1: Amount (रक्कम)
B2: To Opening Balance (सुरुवातीची शिल्लक) | D2: 0
F19: By Closing Balance c/d (अखेरची शिल्लक) | H19: =D20-SUM(H2:H18)
A20: Total (एकूण) | D20: =SUM(D2:D19) | E20: Total (एकूण) | H20: =SUM(H2:H19)

Sheet March
A1: Date (तारीख) [Receipts] | B1: Particulars (तपशील / नावे) | C1: L.F. | D1: Amount (रक्कम) | E1: Date (तारीख) [Payments] | F1: Particulars (तपशील / जमा) | G1: L.F. | H1: Amount (रक्कम)
B2: To Opening Balance (सुरुवातीची शिल्लक) | D2: 0
F19: By Closing Balance c/d (अखेरची शिल्लक) | H19: =D20-SUM(H2:H18)
A20: Total (एकूण) | D20: =SUM(D2:D19) | E20: Total (एकूण) | H20: =SUM(H2:H19)

Sheet April
A1: Date (तारीख) [Receipts] | B1: Particulars (तपशील / नावे) | C1: L.F. | D1: Amount (रक्कम) | E1: Date (तारीख) [Payments] | F1: Particulars (तपशील / जमा) | G1: L.F. | H1: Amount (रक्कम)
B2: To Opening Balance (सुरुवातीची शिल्लक) | D2: 0
F19: By Closing Balance c/d (अखेरची शिल्लक) | H19: =D20-SUM(H2:H18)
A20: Total (एकूण) | D20: =SUM(D2:D19) | E20: Total (एकूण) | H20: =SUM(H2:H19)

Sheet May
A1: Date (तारीख) [Receipts] | B1: Particulars (तपशील / नावे) | C1: L.F. | D1: Amount (रक्कम) | E1: Date (तारीख) [Payments] | F1: Particulars (तपशील / जमा) | G1: L.F. | H1: Amount (रक्कम)
B2: To Opening Balance (सुरुवातीची शिल्लक) | D2: 0
F19: By Closing Balance c/d (अखेरची शिल्लक) | H19: =D20-SUM(H2:H18)
A20: Total (एकूण) | D20: =SUM(D2:D19) | E20: Total (एकूण) | H20: =SUM(H2:H19)

Sheet June
A1: Date (तारीख) [Receipts] | B1: Particulars (तपशील / नावे) | C1: L.F. | D1: Amount (रक्कम) | E1: Date (तारीख) [Payments] | F1: Particulars (तपशील / जमा) | G1: L.F. | H1: Amount (रक्कम)
B2: To Opening Balance (सुरुवातीची शिल्लक) | D2: 0
F19: By Closing Balance c/d (अखेरची शिल्लक) | H19: =D20-SUM(H2:H18)
A20: Total (एकूण) | D20: =SUM(D2:D19) | E20: Total (एकूण) | H20: =SUM(H2:H19)

Sheet July
A1: Date (तारीख) [Receipts] | B1: Particulars (तपशील / नावे) | C1: L.F. | D1: Amount (रक्कम) | E1: Date (तारीख) [Payments] | F1: Particulars (तपशील / जमा) | G1: L.F. | H1: Amount (रक्कम)
B2: To Opening Balance (सुरुवातीची शिल्लक) | D2: 0
F19: By Closing Balance c/d (अखेरची शिल्लक) | H19: =D20-SUM(H2:H18)
A20: Total (एकूण) | D20: =SUM(D2:D19) | E20: Total (एकूण) | H20: =SUM(H2:H19)

Sheet August
A1: Date (तारीख) [Receipts] | B1: Particulars (तपशील / नावे) | C1: L.F. | D1: Amount (रक्कम) | E1: Date (तारीख) [Payments] | F1: Particulars (तपशील / जमा) | G1: L.F. | H1: Amount (रक्कम)
B2: To Opening Balance (सुरुवातीची शिल्लक) | D2: 0
F19: By Closing Balance c/d (अखेरची शिल्लक) | H19: =D20-SUM(H2:H18)
A20: Total (एकूण) | D20: =SUM(D2:D19) | E20: Total (एकूण) | H20: =SUM(H2:H19)

Sheet September
A1: Date (तारीख) [Receipts] | B1: Particulars (तपशील / नावे) | C1: L.F. | D1: Amount (रक्कम) | E1: Date (तारीख) [Payments] | F1: Particulars (तपशील / जमा) | G1: L.F. | H1: Amount (रक्कम)
B2: To Opening Balance (सुरुवातीची शिल्लक) | D2: 0
F19: By Closing Balance c/d (अखेरची शिल्लक) | H19: =D20-SUM(H2:H18)
A20: Total (एकूण) | D20: =SUM(D2:D19) | E20: Total (एकूण) | H20: =SUM(H2:H19)

Sheet October
A1: Date (तारीख) [Receipts] | B1: Particulars (तपशील / नावे) | C1: L.F. | D1: Amount (रक्कम) | E1: Date (तारीख) [Payments] | F1: Particulars (तपशील / जमा) | G1: L.F. | H1: Amount (रक्कम)
B2: To Opening Balance (सुरुवातीची शिल्लक) | D2: 0
F19: By Closing Balance c/d (अखेरची शिल्लक) | H19: =D20-SUM(H2:H18)
A20: Total (एकूण) | D20: =SUM(D2:D19) | E20: Total (एकूण) | H20: =SUM(H2:H19)

Sheet November
A1: Date (तारीख) [Receipts] | B1: Particulars (तपशील / नावे) | C1: L.F. | D1: Amount (रक्कम) | E1: Date (तारीख) [Payments] | F1: Particulars (तपशील / जमा) | G1: L.F. | H1: Amount (रक्कम)
B2: To Opening Balance (सुरुवातीची शिल्लक) | D2: 0
F19: By Closing Balance c/d (अखेरची शिल्लक) | H19: =D20-SUM(H2:H18)
A20: Total (एकूण) | D20: =SUM(D2:D19) | E20: Total (एकूण) | H20: =SUM(H2:H19)

Sheet December
A1: Date (तारीख) [Receipts] | B1: Particulars (तपशील / नावे) | C1: L.F. | D1: Amount (रक्कम) | E1: Date (तारीख) [Payments] | F1: Particulars (तपशील / जमा) | G1: L.F. | H1: Amount (रक्कम)
B2: To Opening Balance (सुरुवातीची शिल्लक) | D2: 0
F19: By Closing Balance c/d (अखेरची शिल्लक) | H19: =D20-SUM(H2:H18)
A20: Total (एकूण) | D20: =SUM(D2:D19) | E20: Total (एकूण) | H20: =SUM(H2:H19)
